i054_pypi_preprocess/__init__.py
i054_pypi_preprocess/core.py
i054_pypi_preprocess-0.1.1.dist-info/licenses/LICENSE
i054_pypi_preprocess-0.1.1.dist-info/METADATA
i054_pypi_preprocess-0.1.1.dist-info/WHEEL
i054_pypi_preprocess-0.1.1.dist-info/top_level.txt
i054_pypi_preprocess-0.1.1.dist-info/RECORD
